ss_rawdata_api/__init__.py
ss_rawdata_api/ss_rawdata_api.py
ss_rawdata_api-0.1.0.dist-info/METADATA
ss_rawdata_api-0.1.0.dist-info/WHEEL
ss_rawdata_api-0.1.0.dist-info/entry_points.txt
ss_rawdata_api-0.1.0.dist-info/top_level.txt
ss_rawdata_api-0.1.0.dist-info/RECORD
