Metadata-Version: 2.1
Name: ss-rawdata-api
Version: 0.1.0
Summary: Python interface for the Sheffield Solar rawdata API endpoints.
Author-email: Jamie Taylor <jamie.taylor@sheffield.ac.uk>
Maintainer-email: Jamie Taylor <jamie.taylor@sheffield.ac.uk>, Julian Briggs <julian.briggs@sheffield.ac.uk>, Andrew Richards <a.c.richards@sheffield.ac.uk>
Project-URL: Homepage, https://docs.google.com/document/d/1cqBbKyWuM5fkYf9qzymYBtwo9VIqtZ8E48Tf8kOzXCA/edit
Project-URL: Bug Reports, https://github.com/SheffieldSolar/SS-RawData-API/issues
Project-URL: Source, https://github.com/SheffieldSolar/SS-RawData-API
Keywords: Sheffield Solar,API,data,solar,pv
Classifier: Development Status :: 4 - Beta
Classifier: Intended Audience :: Developers
Classifier: Programming Language :: Python :: 3
Classifier: Programming Language :: Python :: 3.10
Classifier: Programming Language :: Python :: 3.11
Classifier: Programming Language :: Python :: 3.12
Classifier: Programming Language :: Python :: 3 :: Only
Classifier: Operating System :: OS Independent
Requires-Python: >=3.10
Requires-Dist: pandas
Requires-Dist: requests
Requires-Dist: pyyaml
